daimojo-2.8.9.1.dist-info/WHEEL
daimojo-2.8.9.1.dist-info/RECORD
daimojo-2.8.9.1.dist-info/top_level.txt
daimojo-2.8.9.1.dist-info/METADATA
daimojo-2.8.9.1.dist-info/LICENSE
daimojo-2.8.9.1.data/scripts/mojo_scoring_cli
daimojo/BinaryOp_pb2.py
daimojo/util.py
daimojo/Agg_pb2.py
daimojo/__init__.py
daimojo/cppmojo.cpython-312-x86_64-linux-gnu.so
daimojo/NA_pb2.py
daimojo/Text_pb2.py
daimojo/Tree_pb2.py
daimojo/Group_pb2.py
daimojo/model.py
daimojo/Pipeline_pb2.py
daimojo/Map_pb2.py
daimojo/Datepart_pb2.py
daimojo/NewColumn_pb2.py
daimojo/AsType_pb2.py
daimojo/Custom_pb2.py
daimojo/Ftrl_pb2.py
daimojo/Column_pb2.py
daimojo/Problem_pb2.py
daimojo/__about__.py
daimojo/BUILD_INFO.txt
daimojo/Math_pb2.py
daimojo/tf_2.15.0/libtensorflow_framework.so.2
daimojo/tf_2.15.0/libtensorflow.so
daimojo/pytorch_2.3.0/libgomp-a34b3233.so.1
daimojo/pytorch_2.3.0/libtorch.so
daimojo/pytorch_2.3.0/libtorch_cpu.so
daimojo/pytorch_2.3.0/libpytorch_scorer_c.so
daimojo/pytorch_2.3.0/libc10.so
daimojo/pytorch_vocab_pb/roberta-base-merges-1.pb
daimojo/pytorch_vocab_pb/bert-base-chinese-vocab.pb
daimojo/pytorch_vocab_pb/distilbert-base-uncased-distilled-squad-vocab.pb
daimojo/pytorch_vocab_pb/camembert-base-sentencepiece.bpe.model
daimojo/pytorch_vocab_pb/albert-base-v2-spiece.model
daimojo/pytorch_vocab_pb/roberta-base-merges-2.pb
daimojo/pytorch_vocab_pb/xlm-roberta-large-sentencepiece.bpe.model
daimojo/pytorch_vocab_pb/distilbert-base-uncased-vocab.pb
daimojo/pytorch_vocab_pb/albert-large-v2-spiece.model
daimojo/pytorch_vocab_pb/bert-base-uncased-vocab.pb
daimojo/pytorch_vocab_pb/deberta-v3-base-spiece.model
daimojo/pytorch_vocab_pb/distilbert-base-multilingual-cased-vocab.pb
daimojo/pytorch_vocab_pb/bert-base-multilingual-cased-vocab.pb
daimojo/pytorch_vocab_pb/xlnet-base-cased-spiece.model
daimojo/pytorch_vocab_pb/roberta-base-vocab.pb
daimojo/pytorch_vocab_pb/xlnet-large-cased-spiece.model
daimojo/pytorch_vocab_pb/roberta-base-merges-3.pb
daimojo/pytorch_vocab_pb/albert-xxlarge-v2-spiece.model
daimojo/pytorch_vocab_pb/xlm-roberta-base-sentencepiece.bpe.model
