Metadata-Version: 2.1
Name: daimojo
Version: 2.8.9.1
Summary: DAI mojo scoring package
License: Driverless AI Evaluation Agreement
License-File: LICENSE
Requires-Dist: datatable
Requires-Dist: pandas
Requires-Dist: protobuf ~=4.25
